agentsts/adk/__init__.py
agentsts/adk/_base.py
agentsts_adk-0.0.8.dist-info/METADATA
agentsts_adk-0.0.8.dist-info/WHEEL
agentsts_adk-0.0.8.dist-info/RECORD
