Metadata-Version: 2.4
Name: agentsts-adk
Version: 0.0.8
Summary: Framework-specific integration points with agentsts-core
Requires-Python: >=3.11.0
Requires-Dist: agentsts-core
Requires-Dist: aiofiles>=24.1.0
Requires-Dist: anyio>=4.9.0
Requires-Dist: google-adk>=1.18.0
Requires-Dist: google-auth>=2.40.2
Requires-Dist: google-genai>=1.21.1
Requires-Dist: httpx>=0.25.0
Requires-Dist: pydantic>=2.5.0
Requires-Dist: typing-extensions>=4.8.0
Provides-Extra: test
Requires-Dist: pytest-asyncio>=0.25.3; extra == 'test'
Requires-Dist: pytest-mock>=3.0.0; extra == 'test'
Requires-Dist: pytest>=8.3.5; extra == 'test'
